ls_dlp/__init__.py
ls_dlp/download_live.py
ls_dlp/get_urls.py
ls_dlp/headers.py
ls_dlp/main.py
ls_dlp/monitor_channel.py
ls_dlp/py.typed
ls_dlp/setup_logger.py
ls_dlp/youtube_url.py
ls_dlp-0.0.5.dist-info/METADATA
ls_dlp-0.0.5.dist-info/WHEEL
ls_dlp-0.0.5.dist-info/entry_points.txt
ls_dlp-0.0.5.dist-info/licenses/LICENSE
ls_dlp-0.0.5.dist-info/RECORD
