Metadata-Version: 2.4
Name: ls-dlp
Version: 0.0.5
Summary: Garbage youtube livestream downloader
Project-URL: repository, https://github.com/eggplants/ls_dlp
Author-email: Alex Mckenzie-Hicks <github@canofsocks.com>
Maintainer-email: eggplants <w10776e8w@yahoo.co.jp>
License: This is free and unencumbered software released into the public domain.
License-File: LICENSE
Keywords: download
Classifier: Development Status :: 3 - Alpha
Classifier: Environment :: Console
Classifier: Intended Audience :: Developers
Classifier: Intended Audience :: End Users/Desktop
Classifier: License :: OSI Approved :: The Unlicense (Unlicense)
Classifier: Natural Language :: English
Classifier: Operating System :: OS Independent
Classifier: Programming Language :: Python :: 3 :: Only
Classifier: Programming Language :: Python :: 3.10
Classifier: Programming Language :: Python :: 3.11
Classifier: Programming Language :: Python :: 3.12
Classifier: Programming Language :: Python :: 3.13
Classifier: Programming Language :: Python :: 3.14
Classifier: Programming Language :: Python :: Implementation :: CPython
Classifier: Topic :: Internet
Classifier: Topic :: Multimedia :: Video
Classifier: Topic :: Software Development :: Libraries :: Python Modules
Classifier: Topic :: Utilities
Classifier: Typing :: Typed
Requires-Python: <4,>=3.10
Requires-Dist: httpx>=0.28.1
Requires-Dist: urllib3>=2.6.3
Requires-Dist: yt-dlp-ejs>=0.3.2
Requires-Dist: yt-dlp>=2025.12.8
